transgnn/__init__.py
transgnn-0.0.1.dev0.dist-info/METADATA
transgnn-0.0.1.dev0.dist-info/WHEEL
transgnn-0.0.1.dev0.dist-info/top_level.txt
transgnn-0.0.1.dev0.dist-info/RECORD
