Metadata-Version: 2.1
Name: transgnn
Version: 0.0.1.dev0
Summary: transgnn
Author: Shadow Walker
Keywords: transgnn
Classifier: Programming Language :: Python :: 3
Classifier: Programming Language :: Python :: 3.8
Classifier: Programming Language :: Python :: 3.9
Classifier: Programming Language :: Python :: 3.10
Requires-Dist: torch
